piegy/__init__.py
piegy/__version__.py
piegy/analysis.py
piegy/build_info.py
piegy/data_tools.py
piegy/figures.py
piegy/simulation.py
piegy/simulation_py.py
piegy/test_var.py
piegy/videos.py
piegy/C_core/Makefile
piegy/C_core/model.c
piegy/C_core/model.h
piegy/C_core/patch.c
piegy/C_core/patch.h
piegy/C_core/piegyc.cpython-38-i386-linux-gnu.so
piegy/C_core/runner.c
piegy/C_core/sim_funcs.c
piegy/C_core/sim_funcs.h
piegy/tools/__init__.py
piegy/tools/figure_tools.py
piegy/tools/file_tools.py
piegy/tools/find_C.py
piegy-2.3.1.dist-info/LICENSE.txt
piegy-2.3.1.dist-info/METADATA
piegy-2.3.1.dist-info/WHEEL
piegy-2.3.1.dist-info/top_level.txt
piegy-2.3.1.dist-info/RECORD
