Metadata-Version: 2.4
Name: piegy
Version: 2.3.1
Summary: Payoff-Driven Stochastic Spatial Model for Evolutionary Game Theory
Author-email: Chenning Xu <cxu7@caltech.edu>
License: BSD 3-Clause License
Project-URL: Source, https://github.com/Chenning04/piegy.git
Project-URL: Documentation, https://piegy.readthedocs.io/en/
Keywords: Game Theory,Evolutionary Game Theory,Spatial Model,Stochastic Model,Payoff Driven
Classifier: Development Status :: 4 - Beta
Classifier: Intended Audience :: Developers
Classifier: Intended Audience :: Science/Research
Classifier: Intended Audience :: Education
Classifier: License :: OSI Approved :: BSD License
Classifier: Programming Language :: Python :: 3
Classifier: Programming Language :: Python :: 3.10
Classifier: Programming Language :: Python :: 3.11
Classifier: Operating System :: OS Independent
Requires-Python: >=3.7
License-File: LICENSE.txt
Requires-Dist: numpy
Requires-Dist: matplotlib
Requires-Dist: moviepy>=2.1.1
Requires-Dist: opencv-python>=4
Dynamic: license-file
